<?xml version="1.0" encoding="UTF-8"?>
<!DOCTYPE mapper PUBLIC "-//mybatis.org//DTD Mapper 3.0//EN" "http://mybatis.org/dtd/mybatis-3-mapper.dtd">
<mapper namespace="com.Aview.mapper.MemberMapper">
	<insert id="stuJoin">
		INSERT INTO TBL_STUDENT
(UID, UPWD, UPWDQ, UPWDA, ULASTNAME, UFIRSTNAME, UEMAIL, UBIRTH, UPHONE, UZIPCODE, UADDRESS, UADDRESSDETAIL)
VALUES(#{uid}, #{upwd}, #{upwdq}, #{upwda}, #{ulastname}, #{ufirstname}, #{uemail}, #{ubirth},
#{uphone}, #{uzipcode}, #{uaddress}, #{uaddressdetail})
	</insert>
	
	<select id="checkId" resultType="int">
	SELECT COUNT(*) FROM TBL_STUDENT WHERE UID = #{uid}	
	</select>
	
	<select id="stuLogin" resultType="int">
	SELECT COUNT(*) FROM TBL_STUDENT WHERE UID = #{uid} AND UPWD = #{upwd}
	</select>
	
	<insert id="acaJoin">
		INSERT INTO TBL_ACADEMY
(ANAME, AID, ACORPORATE, APWD, APWDQ, APWDA, AEMAIL, APHONE, AZIPCODE, AADDRESS, AADDRESSDETAIL)
VALUES(#{Aname}, #{Aid}, #{Acorporate}, #{Apwd}, #{Apwdq}, #{Apwda}, #{Aemail},
#{Aphone}, #{Azipcode}, #{Aaddress}, #{Aaddressdetail})
	</insert>
	
	<select id="checkIdAca" resultType="int">
	SELECT COUNT(*) FROM TBL_ACADEMY WHERE AID = #{Aid}	
	</select>
	
	<select id="acaLogin" resultType="int">
	SELECT COUNT(*) FROM TBL_ACADEMY WHERE AID = #{Aid} AND APWD = #{Apwd}
	</select>

</mapper>













